{
  "cli": {
    "version": ">= 12.0.0",
    "appVersionSource": "remote"
  },
  "build": {
    "development": {
      "developmentClient": true,
      "distribution": "internal",
      "android": {
        "buildType": "apk"
      },
      "env": {
        "EXPO_PUBLIC_SUPABASE_URL": "https://vnmdavbdlgilkdaduipq.supabase.co",
        "EXPO_PUBLIC_SUPABASE_ANON_KEY": "sb_publishable_INepS-RnimeTkn_S9WTwvQ_nckXs168"
      }
    },
    "preview": {
      "distribution": "internal",
      "android": {
        "buildType": "apk"
      },
      "env": {
        "EXPO_PUBLIC_SUPABASE_URL": "https://vnmdavbdlgilkdaduipq.supabase.co",
        "EXPO_PUBLIC_SUPABASE_ANON_KEY": "sb_publishable_INepS-RnimeTkn_S9WTwvQ_nckXs168"
      }
    },
    "production": {
      "autoIncrement": true,
      "android": {
        "image": "latest",
        "buildType": "app-bundle"
      },
      "env": {
        "EXPO_PUBLIC_SUPABASE_URL": "https://vnmdavbdlgilkdaduipq.supabase.co",
        "EXPO_PUBLIC_SUPABASE_ANON_KEY": "sb_publishable_INepS-RnimeTkn_S9WTwvQ_nckXs168"
      }
    }
  },
  "submit": {
    "production": {
      "android": {
        "track": "internal"
      }
    }
  }
}
